goastpy/__init__.py
goastpy/goastparser.h
goastpy/goastparser.so
goastpy/goastparser_Darwin.h
goastpy/goastparser_Darwin.so
goastpy/goastparser_Linux.h
goastpy/goastparser_Linux.so
goastpy/goastparser_wrapper.py
goastpy/goastpy.py
goastpy-0.1.9.dist-info/LICENSE
goastpy-0.1.9.dist-info/METADATA
goastpy-0.1.9.dist-info/WHEEL
goastpy-0.1.9.dist-info/top_level.txt
goastpy-0.1.9.dist-info/RECORD
